{
  "$schema": "https://developer.microsoft.com/json-schemas/fabric/item/report/definition/visualContainer/2.5.0/schema.json",
  "name": "be2bb44a6f443200ba90",
  "position": {
    "x": 0,
    "y": 383.72201955969393,
    "z": 2000,
    "height": 147.67483783054888,
    "width": 265.11703169578857,
    "tabOrder": 2000
  },
  "visual": {
    "visualType": "slicer",
    "query": {
      "queryState": {
        "Values": {
          "projections": [
            {
              "field": {
                "Column": {
                  "Expression": {
                    "SourceRef": {
                      "Entity": "Customer"
                    }
                  },
                  "Property": "Customer"
                }
              },
              "queryRef": "Customer.Customer",
              "nativeQueryRef": "Customer",
              "active": true
            }
          ]
        }
      }
    },
    "objects": {
      "data": [
        {
          "properties": {
            "mode": {
              "expr": {
                "Literal": {
                  "Value": "'Basic'"
                }
              }
            }
          }
        }
      ],
      "general": [
        {
          "properties": {}
        }
      ]
    },
    "drillFilterOtherVisuals": true
  },
  "filterConfig": {
    "filters": [
      {
        "name": "052de290ebb96eda62ff",
        "field": {
          "Column": {
            "Expression": {
              "SourceRef": {
                "Entity": "Customer"
              }
            },
            "Property": "Customer"
          }
        },
        "type": "Categorical",
        "filter": {
          "Version": 2,
          "From": [
            {
              "Name": "c",
              "Entity": "Customer",
              "Type": 0
            }
          ],
          "Where": [
            {
              "Condition": {
                "Not": {
                  "Expression": {
                    "In": {
                      "Expressions": [
                        {
                          "Column": {
                            "Expression": {
                              "SourceRef": {
                                "Source": "c"
                              }
                            },
                            "Property": "Customer"
                          }
                        }
                      ],
                      "Values": [
                        [
                          {
                            "Literal": {
                              "Value": "null"
                            }
                          }
                        ]
                      ]
                    }
                  }
                }
              }
            }
          ]
        },
        "objects": {
          "general": [
            {
              "properties": {
                "isInvertedSelectionMode": {
                  "expr": {
                    "Literal": {
                      "Value": "true"
                    }
                  }
                }
              }
            }
          ]
        }
      }
    ]
  }
}