{
  "$schema": "https://developer.microsoft.com/json-schemas/fabric/item/report/definition/visualContainer/2.5.0/schema.json",
  "name": "0c93e1e9dd54f0300c0c",
  "position": {
    "x": 0,
    "y": 148.83763182921462,
    "z": 1000,
    "height": 234.88438773047932,
    "width": 212.79130175583029,
    "tabOrder": 1000
  },
  "visual": {
    "visualType": "slicer",
    "query": {
      "queryState": {
        "Values": {
          "projections": [
            {
              "field": {
                "HierarchyLevel": {
                  "Expression": {
                    "Hierarchy": {
                      "Expression": {
                        "SourceRef": {
                          "Entity": "City"
                        }
                      },
                      "Hierarchy": "Geography"
                    }
                  },
                  "Level": "State Province"
                }
              },
              "queryRef": "City.Geography.State Province",
              "nativeQueryRef": "Geography State Province",
              "active": true
            },
            {
              "field": {
                "HierarchyLevel": {
                  "Expression": {
                    "Hierarchy": {
                      "Expression": {
                        "SourceRef": {
                          "Entity": "City"
                        }
                      },
                      "Hierarchy": "Geography"
                    }
                  },
                  "Level": "City"
                }
              },
              "queryRef": "City.Geography.City",
              "nativeQueryRef": "Geography City",
              "active": false
            }
          ]
        }
      }
    },
    "expansionStates": [
      {
        "roles": [
          "Values"
        ],
        "levels": [
          {
            "queryRefs": [
              "City.Geography.State Province"
            ],
            "isCollapsed": true,
            "isPinned": true
          },
          {
            "queryRefs": [
              "City.Geography.City"
            ],
            "isCollapsed": true
          }
        ],
        "root": {}
      }
    ],
    "objects": {
      "data": [
        {
          "properties": {
            "mode": {
              "expr": {
                "Literal": {
                  "Value": "'Basic'"
                }
              }
            }
          }
        }
      ],
      "general": [
        {
          "properties": {}
        }
      ]
    },
    "drillFilterOtherVisuals": true
  },
  "filterConfig": {
    "filters": [
      {
        "name": "d9401fca2723ee45a4b9",
        "field": {
          "Column": {
            "Expression": {
              "SourceRef": {
                "Entity": "City"
              }
            },
            "Property": "City"
          }
        },
        "type": "Categorical",
        "filter": {
          "Version": 2,
          "From": [
            {
              "Name": "c",
              "Entity": "City",
              "Type": 0
            }
          ],
          "Where": [
            {
              "Condition": {
                "Not": {
                  "Expression": {
                    "In": {
                      "Expressions": [
                        {
                          "Column": {
                            "Expression": {
                              "SourceRef": {
                                "Source": "c"
                              }
                            },
                            "Property": "City"
                          }
                        }
                      ],
                      "Values": [
                        [
                          {
                            "Literal": {
                              "Value": "null"
                            }
                          }
                        ]
                      ]
                    }
                  }
                }
              }
            }
          ]
        },
        "howCreated": "User",
        "objects": {
          "general": [
            {
              "properties": {
                "isInvertedSelectionMode": {
                  "expr": {
                    "Literal": {
                      "Value": "true"
                    }
                  }
                }
              }
            }
          ]
        }
      }
    ]
  }
}